Workbook
Name rendimento_carteira: Principal!$D$16
Name salario: Principal!$D$15
Name taxa_rendimento: Principal!$D$22

Sheet Principal
B14: CONFIGURAÇÕES
B15: Salário | D15: 1100
B16: Rendimento Carteira | D16: 0.01
B17: Sugestão de investimento | D17: =D15*10% -> 110
B19: INVESTIMENTO MENSAL
B20: Quanto Investir Por Mês? | D20: =D17 -> 110
B21: Por Quantos Anos? | D21: 5
B22: Taxa De Rendimento Mensal? | D22: 0.0108
B23: Patrimonio Acumulado? | D23: =FV(D22, D21*12,D20)*-1 -> 9218.4421
B24: Dividendos Mensais? | D24: =D23*0.1 -> 921.84421
B26: CENÁRIOS | D26: DIVIDENDO
A27: 1 | B27: Quanto em 1 ano? | C27: =FV($D$22, A27*12,$D$20)*(-1) -> 1401.3005 | D27: =C27*$D$16 -> 14.013005
A28: 2 | B28: Quanto em 2 anos? | C28: =FV($D$22, A28*12,$D$20)*(-1) -> 2995.395 | D28: =C28*$D$16 -> 29.95395
A29: 5 | B29: Quanto em 5 anos? | C29: =FV($D$22, A29*12,$D$20)*(-1) -> 9218.4421 | D29: =C29*$D$16 -> 92.184421
A30: 10 | B30: Quanto em 10 anos? | C30: =FV($D$22, A30*12,$D$20)*(-1) -> 26780.343 | D30: =C30*$D$16 -> 267.80343
A31: 20 | B31: Quanto em 20 anos? | C31: =FV($D$22, A31*12,$D$20)*(-1) -> 123975.39 | D31: =C31*$D$16 -> 1239.7539
B34: PERFIL | C34: MODERADO
B35: VALOR A SER INVESTIDO POR MÊS | C35: =D20 -> 110
B37: TIPO DE FII | C37: % SUGERIDO | D37: VALORES
B38: PAPEL | C38: =VLOOKUP($C$34&"-"&B38, Tipo_de_FIIs!A1:D19, 4,FALSE ) -> 0.32 | D38: =C38*$C$35 -> 35.2
B39: TIJOLO | C39: =VLOOKUP($C$34&"-"&B39, Tipo_de_FIIs!A2:D20, 4,FALSE ) -> 0.4 | D39: =C39*$C$35 -> 44
B40: HIBRIDOS | C40: =VLOOKUP($C$34&"-"&B40, Tipo_de_FIIs!A3:D21, 4,FALSE ) -> 0.08 | D40: =C40*$C$35 -> 8.8
B41: FOFs | C41: =VLOOKUP($C$34&"-"&B41, Tipo_de_FIIs!A4:D22, 4,FALSE ) -> 0.1 | D41: =C41*$C$35 -> 11
B42: DESENVOLVIMENTO | C42: =VLOOKUP($C$34&"-"&B42, Tipo_de_FIIs!A5:D23, 4,FALSE ) -> 0.1 | D42: =C42*$C$35 -> 11
B43: HOTELARIAS | C43: =VLOOKUP($C$34&"-"&B43, Tipo_de_FIIs!A6:D24, 4,FALSE ) -> 0 | D43: =C43*$C$35 -> 0
D44: =SUM(D38:D43) -> 110

Sheet Tipo_de_FIIs
A1: CHAVE | B1: TIPO DE FII | C1: PERFIL | D1: %
A2: =C2&"-"&B2 -> CONSERVADOR-PAPEL | B2: PAPEL | C2: CONSERVADOR | D2: 0.3
A3: =C3&"-"&B3 -> CONSERVADOR-TIJOLO | B3: TIJOLO | C3: CONSERVADOR | D3: 0.5
A4: =C4&"-"&B4 -> CONSERVADOR-HIBRIDOS | B4: HIBRIDOS | C4: CONSERVADOR | D4: 0.1
A5: =C5&"-"&B5 -> CONSERVADOR-FOFs | B5: FOFs | C5: CONSERVADOR | D5: 0.1
A6: =C6&"-"&B6 -> CONSERVADOR-DESENVOLVIMENTO | B6: DESENVOLVIMENTO | C6: CONSERVADOR | D6: 0
A7: =C7&"-"&B7 -> CONSERVADOR-HOTELARIAS | B7: HOTELARIAS | C7: CONSERVADOR | D7: 0
A8: =C8&"-"&B8 -> MODERADO-PAPEL | B8: PAPEL | C8: MODERADO | D8: 0.32
A9: =C9&"-"&B9 -> MODERADO-TIJOLO | B9: TIJOLO | C9: MODERADO | D9: 0.4
A10: =C10&"-"&B10 -> MODERADO-HIBRIDOS | B10: HIBRIDOS | C10: MODERADO | D10: 0.08
A11: =C11&"-"&B11 -> MODERADO-FOFs | B11: FOFs | C11: MODERADO | D11: 0.1
A12: =C12&"-"&B12 -> MODERADO-DESENVOLVIMENTO | B12: DESENVOLVIMENTO | C12: MODERADO | D12: 0.1
A13: =C13&"-"&B13 -> MODERADO-HOTELARIAS | B13: HOTELARIAS | C13: MODERADO | D13: 0
... A19: =C19&"-"&B19 -> AGRESSIVO-HOTELARIAS | B19: HOTELARIAS | C19: AGRESSIVO | D19: 0.1
